{
  "wcid": 480637,
  "weenieType": 64,
  "boolStats": [
    {
      "key": 13,
      "value": 1
    },
    {
      "key": 15,
      "value": 1
    },
    {
      "key": 22,
      "value": 1
    },
    {
      "key": 69,
      "value": 0
    }
  ],
  "intStats": [
    {
      "key": 1,
      "value": 128
    },
    {
      "key": 3,
      "value": 14
    },
    {
      "key": 5,
      "value": 150
    },
    {
      "key": 8,
      "value": 25
    },
    {
      "key": 9,
      "value": 0
    },
    {
      "key": 16,
      "value": 32
    },
    {
      "key": 19,
      "value": 250
    },
    {
      "key": 33,
      "value": 1
    },
    {
      "key": 93,
      "value": 1044
    },
    {
      "key": 150,
      "value": 103
    },
    {
      "key": 151,
      "value": 2
    },
    {
      "key": 197,
      "value": 16
    },
    {
      "key": 280,
      "value": 3
    }
  ],
  "didStats": [
    {
      "key": 1,
      "value": 33558202
    },
    {
      "key": 3,
      "value": 536870932
    },
    {
      "key": 6,
      "value": 67114164
    },
    {
      "key": 7,
      "value": 268435723
    },
    {
      "key": 8,
      "value": 100690745
    },
    {
      "key": 22,
      "value": 872415275
    },
    {
      "key": 28,
      "value": 5156
    }
  ],
  "iidStats": [],
  "floatStats": [
    {
      "key": 39,
      "value": 2.0
    },
    {
      "key": 54,
      "value": 3.0
    },
    {
      "key": 167,
      "value": 10.0
    }
  ],
  "int64Stats": [],
  "stringStats": [
    {
      "key": 1,
      "value": "Virindi Consul Essence"
    },
    {
      "key": 14,
      "value": "This item can be placed on wall hooks, where it can be used to cast Virindi Whisper V"
    }
  ],
  "emoteTable": [
    {
      "key": 7,
      "value": [
        {
          "category": 7,
          "emotes": [
            {
              "type": 19,
              "delay": 0.0,
              "extent": 1.0,
              "spellid": 5156
            }
          ],
          "probability": 1.0
        }
      ]
    }
  ],
  "lastModified": "2023-08-22T19:55:51.0554355Z",
  "modifiedBy": "ACE.Adapter",
  "changelog": [
    {
      "created": "2023-08-20T23:07:11.9666527Z",
      "author": "ACE.Adapter",
      "comment": "Weenie exported from ACEmulator world database using ACE.Adapter"
    },
    {
      "created": "2023-08-21T00:37:31.5085512Z",
      "author": "ACE.Adapter",
      "comment": "Weenie exported from ACEmulator world database using ACE.Adapter"
    },
    {
      "created": "2023-08-22T19:55:51.0404701Z",
      "author": "ACE.Adapter",
      "comment": "Weenie exported from ACEmulator world database using ACE.Adapter"
    }
  ],
  "userChangeSummary": "Weenie exported from ACEmulator world database using ACE.Adapter",
  "isDone": false
}